bumpversion/__init__.py
bumpversion/__main__.py
bumpversion/functions.py
bumpversion/version_part.py
bumpversion_kando-0.5.5.dist-info/DESCRIPTION.rst
bumpversion_kando-0.5.5.dist-info/METADATA
bumpversion_kando-0.5.5.dist-info/RECORD
bumpversion_kando-0.5.5.dist-info/WHEEL
bumpversion_kando-0.5.5.dist-info/entry_points.txt
bumpversion_kando-0.5.5.dist-info/metadata.json
bumpversion_kando-0.5.5.dist-info/top_level.txt
